kivy_remote_control/__init__.py
kivy_remote_control/joystick.py
kivy_remote_control/joystickpad.py
kivy_remote_control/touchdata.py
kivy_remote_control-0.0.1.dist-info/LICENSE.txt
kivy_remote_control-0.0.1.dist-info/METADATA
kivy_remote_control-0.0.1.dist-info/WHEEL
kivy_remote_control-0.0.1.dist-info/top_level.txt
kivy_remote_control-0.0.1.dist-info/RECORD
