Metadata-Version: 2.1
Name: kivy_remote_control
Version: 0.0.1
Summary: A kivy remote controll app for mavsdk
Author: uberkie
Author-email: uberkie <aj@datainc.co.za>
License: Copyright (c) 2016 The Python Packaging Authority (PyPA)
Project-URL: Homepage, https://github.com/pypa/sampleproject
Keywords: kivy,mavlink,mavsdk,joystick,android
Classifier: Development Status :: 4 - Beta
Classifier: Programming Language :: Python
Requires-Python: >3.6, <=3.11
License-File: LICENSE.txt
Requires-Dist: kivy
